CHANGES.txt
MANIFEST.in
README.txt
setup.py
dateable/__init__.py
dateable.kalends.egg-info/PKG-INFO
dateable.kalends.egg-info/SOURCES.txt
dateable.kalends.egg-info/dependency_links.txt
dateable.kalends.egg-info/entry_points.txt
dateable.kalends.egg-info/namespace_packages.txt
dateable.kalends.egg-info/not-zip-safe
dateable.kalends.egg-info/requires.txt
dateable.kalends.egg-info/top_level.txt
dateable/kalends/__init__.py
doc/USING.txt